<cac:TaxSubtotal xmlns="urn:oasis:names:specification:ubl:schema:xsd:Invoice-2" xmlns:cac="urn:oasis:names:specification:ubl:schema:xsd:CommonAggregateComponents-2" xmlns:cbc="urn:oasis:names:specification:ubl:schema:xsd:CommonBasicComponents-2" xmlns:ext="urn:oasis:names:specification:ubl:schema:xsd:CommonExtensionComponents-2">
    <cbc:TaxableAmount currencyID="SAR">{{taxable_amount}}</cbc:TaxableAmount>
    <cbc:TaxAmount currencyID="SAR">{{tax_amount}}</cbc:TaxAmount>
    <cac:TaxCategory>
        <cbc:ID>{{classified_tax_category}}</cbc:ID>
        <cbc:Percent>{{tax_rate}}</cbc:Percent>
        <cbc:TaxExemptionReasonCode>{{tax_exemption_reason_code}}</cbc:TaxExemptionReasonCode>
        <cbc:TaxExemptionReason>{{tax_exemption_reason}}</cbc:TaxExemptionReason>
        <cac:TaxScheme>
            <cbc:ID>VAT</cbc:ID>
        </cac:TaxScheme>
    </cac:TaxCategory>
</cac:TaxSubtotal>